analyzer/__init__.py
analyzer/java_analyzer.py
analyzer/javascript_analyzer.py
analyzer/js_analyzer.py
analyzer/python_analyzer.py
analyzer/rust_analyzer.py
fetcher/__init__.py
fetcher/fetcher.py
resolver/__init__.py
resolver/resolver_engine.py
polydepend-1.2.1.dist-info/LICENSE.txt
polydepend-1.2.1.dist-info/METADATA
polydepend-1.2.1.dist-info/WHEEL
polydepend-1.2.1.dist-info/entry_points.txt
polydepend-1.2.1.dist-info/top_level.txt
polydepend-1.2.1.dist-info/RECORD
