Metadata-Version: 2.1
Name: polydepend
Version: 1.2.1
Summary: Multi-language Dependency Management Tool
Home-page: https://github.com/Simacoder/polydepend
Author: Simanga Mchunu
Author-email: datawithsima@gmail.com
Classifier: Development Status :: 3 - Alpha
Classifier: Intended Audience :: Developers
Classifier: License :: OSI Approved :: MIT License
Classifier: Programming Language :: Python :: 3.7
Classifier: Programming Language :: Python :: 3.8
Classifier: Programming Language :: Python :: 3.9
Classifier: Topic :: Software Development :: Libraries :: Python Modules
Classifier: Topic :: System :: Software Distribution
Requires-Python: >=3.7
License-File: LICENSE.txt
Requires-Dist: requests>=2.25.0
Requires-Dist: packaging
Provides-Extra: dev
Requires-Dist: pytest; extra == "dev"
Requires-Dist: coverage; extra == "dev"
Requires-Dist: black; extra == "dev"
Requires-Dist: mypy; extra == "dev"
